README.md
setup.cfg
setup.py
declarative_parser/__init__.py
declarative_parser/constructor_parser.py
declarative_parser/parser.py
declarative_parser/types.py
declarative_parser.egg-info/PKG-INFO
declarative_parser.egg-info/SOURCES.txt
declarative_parser.egg-info/dependency_links.txt
declarative_parser.egg-info/top_level.txt