Metadata-Version: 1.1
Name: declarative-parser
Version: 0.1.3
Summary:  Modern, declarative argument parser for Python 3.6+
Home-page: https://github.com/krassowski/declarative-parser
Author: Michal Krassowski
Author-email: krassowski.michal+pypi@gmail.com
License: MIT
Download-URL: https://github.com/krassowski/declarative-parser/tarball/v0.1.3
Keywords: argument,parser,argparse,declarative,cli
Platform: UNKNOWN
Classifier: Development Status :: 4 - Beta
Classifier: License :: OSI Approved :: MIT License
Classifier: Operating System :: Microsoft :: Windows
Classifier: Operating System :: POSIX :: Linux
Classifier: Environment :: Console
Classifier: Topic :: Utilities
Classifier: Topic :: Software Development :: User Interfaces
Classifier: Topic :: Software Development :: Libraries :: Python Modules
Classifier: Intended Audience :: Developers
Classifier: Programming Language :: Python :: 3.6
Classifier: Programming Language :: Python :: 3.7
